AUTHORS
LICENSE
MANIFEST.in
README.rst
jscov8.py
setup.py
jscov8.egg-info/PKG-INFO
jscov8.egg-info/SOURCES.txt
jscov8.egg-info/dependency_links.txt
jscov8.egg-info/top_level.txt