Metadata-Version: 1.1
Name: jscov8
Version: 0.1.0
Summary: JavaScript coverage tool built with Python and V8.
Home-page: http://github.com/damoti/jscov8
Author: Lex Berezhny
Author-email: lex@damoti.com
License: Apache Software License
Keywords: js javascript coverage pyv8 v8 pyjx
Platform: unix
Platform: linux
Platform: osx
Platform: cygwin
Platform: win32
Classifier: Programming Language :: Python
Classifier: Programming Language :: JavaScript
Classifier: Development Status :: 3 - Alpha
Classifier: Environment :: Console
Classifier: Environment :: Web Environment
Classifier: Intended Audience :: Developers
Classifier: License :: OSI Approved :: Apache Software License
Classifier: Operating System :: OS Independent
Classifier: Topic :: Software Development
Classifier: Topic :: Software Development :: Build Tools
Classifier: Topic :: Software Development :: Code Generators
Classifier: Topic :: Software Development :: Pre-processors
Classifier: Topic :: Utilities
